cymple/__init__.py
cymple/__main__.py
cymple/builder.py
cymple/typedefs.py
cymple/version.py
cymple-0.12.0.dist-info/LICENSE
cymple-0.12.0.dist-info/METADATA
cymple-0.12.0.dist-info/WHEEL
cymple-0.12.0.dist-info/top_level.txt
cymple-0.12.0.dist-info/RECORD
