Metadata-Version: 2.1
Name: cymple
Version: 0.12.0
Summary: A productivity enhancer for creating Cypher queries in Python
Requires-Python: >=3.8
License-File: LICENSE
